MANIFEST.in
README.md
setup.cfg
setup.py
sphinx_cloud_theme/__init__.py
sphinx_cloud_theme/breadcrumbs.html
sphinx_cloud_theme/footer.html
sphinx_cloud_theme/gfooter.html
sphinx_cloud_theme/header.html
sphinx_cloud_theme/layout.html
sphinx_cloud_theme/search.html
sphinx_cloud_theme/searchbox.html
sphinx_cloud_theme/side.html
sphinx_cloud_theme/theme.conf
sphinx_cloud_theme/tools.html
sphinx_cloud_theme.egg-info/PKG-INFO
sphinx_cloud_theme.egg-info/SOURCES.txt
sphinx_cloud_theme.egg-info/dependency_links.txt
sphinx_cloud_theme.egg-info/entry_points.txt
sphinx_cloud_theme.egg-info/not-zip-safe
sphinx_cloud_theme.egg-info/requires.txt
sphinx_cloud_theme.egg-info/top_level.txt
sphinx_cloud_theme/static/css/theme.css
sphinx_cloud_theme/static/js/theme.996d405aa2549824ab02.js